{
    "chapter": 19,
    "title": "The Heavenly Rejoicing and the Rider on the White Horse",
    "summary": "Summary for Revelation 19. This chapter reveals prophetic visions, the ultimate triumph of Christ, and encouragement for the faithful to persevere.",
    "faq": [
      {
        "question": "What is a key message in Revelation 19?",
        "answer": "God is sovereign, judgment is certain, and Christ will return to reign in victory."
      },
      {
        "question": "What does Revelation 19 reveal about the end times?",
        "answer": "It offers symbolic imagery of final events, divine justice, and eternal hope for believers."
      }
    ]
  }