{
    "chapter": 15,
    "title": "The Vine and the Branches",
    "summary": "Summary for John 15. This chapter highlights the divine nature of Jesus, His miraculous signs, and His call to believe.",
    "faq": [
      {
        "question": "What is a key message in John 15?",
        "answer": "Jesus is the Son of God who brings eternal life to those who believe."
      },
      {
        "question": "What does John 15 teach about Jesus?",
        "answer": "It emphasizes His divinity, compassion, and redemptive mission."
      }
    ]
  }